Metadata-Version: 1.0
Name: ahmed-package
Version: 1.0
Summary: Gaussian and Binomial distributions
Home-page: UNKNOWN
Author: Ahmed Gaal
Author-email: ahmedito14@gmail.com
License: UNKNOWN
Platform: UNKNOWN
